{"train_samples": 1000, "test_samples": 200, "source_model": "google/mt5-base", "source_dim": 768, "target_dim": 512, "test_results": {"bleu": 0.96, "bleu1": 16.84, "bleu2": 1.69, "bleu3": 0.29, "bleu4": 0.11, "rougeL": 0.1248, "rouge1": 0.1422, "rouge2": 0.0138, "exact_match": 0.0}, "loss": {"X_Y_COS": 0.9022016525268555, "X_Y_MSEloss": 0.00045285248779691756, "X_Y_test_COS": 0.0941648855805397, "X_Y_test_MSEloss": 0.008230847306549549, "X_Y_val_COS": 0.027744807302951813, "X_Y_val_MSEloss": 0.010065820999443531}}